bionemo/size_aware_batching/__init__.py
bionemo/size_aware_batching/sampler.py
bionemo/size_aware_batching/utils.py
bionemo_size_aware_batching-1.0.0.dist-info/licenses/LICENSE
bionemo_size_aware_batching-1.0.0.dist-info/METADATA
bionemo_size_aware_batching-1.0.0.dist-info/WHEEL
bionemo_size_aware_batching-1.0.0.dist-info/top_level.txt
bionemo_size_aware_batching-1.0.0.dist-info/RECORD
