Metadata-Version: 2.4
Name: bionemo-size-aware-batching
Version: 1.0.0
Summary: Provides a simple way to create mini-batches in a memory consumption-aware manner, making it useful for tasks like training models on datasets with varying memory requirements.
Author-email: BioNeMo Team <bionemofeedback@nvidia.com>
License: 
Requires-Python: >=3.10
License-File: LICENSE
Requires-Dist: bionemo-core
Dynamic: license-file
